lento/__init__.py
lento/cfg.py
lento/classes.py
lento/const.py
lento/copyr.py
lento/ly.py
lento/main.py
lento/misc.py
lento/pitch.py
lento/process.py
lento/rhythm.py
lento/version.py
lento-301024.dist-info/LICENSE
lento-301024.dist-info/METADATA
lento-301024.dist-info/WHEEL
lento-301024.dist-info/top_level.txt
lento-301024.dist-info/RECORD
