Metadata-Version: 2.1
Name: lento
Version: 301024
Summary: Programmatically generate Lilypond scores, with ease and elegance of pure Python
Home-page: 
Author: Amir Teymuri
Author-email: Amir Teymuri <amtework@gmail.com>
Project-URL: Homepage, https://lento.codeberg.page/
Classifier: Programming Language :: Python :: 3
Classifier: License :: OSI Approved :: GNU Affero General Public License v3
Classifier: Operating System :: OS Independent
Requires-Python: >=3.5
License-File: LICENSE
Requires-Dist: pytest
